pypremise/Premise_Applesilicon
pypremise/Premise_Linux
pypremise/Premise_Windows.exe
pypremise/__init__.py
pypremise/core.py
pypremise/data_loaders.py
pypremise/io.py
pypremise-0.2.1.dist-info/licenses/LICENSE
pypremise-0.2.1.dist-info/METADATA
pypremise-0.2.1.dist-info/WHEEL
pypremise-0.2.1.dist-info/top_level.txt
pypremise-0.2.1.dist-info/RECORD
