Metadata-Version: 2.4
Name: pypremise
Version: 0.2.1
Summary: Python wrapper for the Premise algorithm, a data mining method to identify significant differences between two groups of texts.
Author-email: "Michael A. Hedderich" <replace-with-lastname@cis.lmu.de>
License: MIT
Requires-Python: >=3.8
License-File: LICENSE
Dynamic: license-file
